furg_imef_verificador_respostas/__init__.py
furg_imef_verificador_respostas/verificador.py
furg_imef_verificador_respostas-0.0.4.dist-info/LICENSE
furg_imef_verificador_respostas-0.0.4.dist-info/METADATA
furg_imef_verificador_respostas-0.0.4.dist-info/WHEEL
furg_imef_verificador_respostas-0.0.4.dist-info/top_level.txt
furg_imef_verificador_respostas-0.0.4.dist-info/RECORD
