Metadata-Version: 2.1
Name: furg-imef-verificador-respostas
Version: 0.0.4
Summary: Verificador de respostas numéricas para problemas de laboratórios do IMEF.
Home-page: https://github.com/LaboratorioIPythonFURG/verificador_respostas
Author: FURG - IMEF
License: Unlicense
Platform: UNKNOWN
Classifier: Programming Language :: Python :: 3
Classifier: License :: OSI Approved :: The Unlicense (Unlicense)
Classifier: Operating System :: OS Independent
Requires-Python: >=3.6
License-File: LICENSE
Requires-Dist: numpy
